{
    "boxes": [
        {
            "id": "1",
            "label": "DHelmetP1Helmet",
            "x": "1033.53",
            "y": "627.69",
            "width": "101.06",
            "height": "116.70",
            "confidence": null
        },
        {
            "id": "2",
            "label": "DHelmet",
            "x": "843.06",
            "y": "334.58",
            "width": "30.12",
            "height": "53.84",
            "confidence": null
        },
        {
            "id": "3",
            "label": "DHelmet",
            "x": "929.38",
            "y": "692.17",
            "width": "58.76",
            "height": "55.67",
            "confidence": null
        }
    ],
    "height": 720,
    "key": "medellin_19.jpg",
    "width": 1280
}